househunt
