Metadata-Version: 1.1
Name: househunt
Version: 0.6.4
Summary: Python module to search Redfin and combine with results from the Zillow API
Home-page: https://github.com/althor880/househunt
Author: AlThor880
Author-email: althor880@gmail.com
License: UNKNOWN
Download-URL: https://github.com/althor880/househunt/tarball/0.6.4
Keywords: house,realty,zillow,redfin,api
Platform: UNKNOWN
